README.md
setup.cfg
setup.py
disease.py.egg-info/PKG-INFO
disease.py.egg-info/SOURCES.txt
disease.py.egg-info/dependency_links.txt
disease.py.egg-info/requires.txt
disease.py.egg-info/top_level.txt
diseaseapi/__init__.py
diseaseapi/client.py
diseaseapi/covid.py
diseaseapi/covidendpoints.py
diseaseapi/covidstatistics.py
diseaseapi/exceptions.py
diseaseapi/influenza.py
diseaseapi/influenzaendpoints.py
diseaseapi/influenzastatistics.py
diseaseapi/request.py
diseaseapi/utils.py