Metadata-Version: 2.1
Name: disease.py
Version: 1.1.0
Summary: An asynchronous wrapper for the Open Disease API written in Python.
Home-page: https://github.com/apex2504/disease.py
Author: Rob Wainwright
Author-email: wainwrightbobby@gmail.com
License: MIT
Keywords: coronavirus,covid-19
Platform: UNKNOWN
Classifier: Development Status :: 5 - Production/Stable
Classifier: License :: OSI Approved :: MIT License
Classifier: Programming Language :: Python :: 3
Classifier: Programming Language :: Python :: 3.5
Classifier: Programming Language :: Python :: 3.6
Classifier: Programming Language :: Python :: 3.7
Classifier: Programming Language :: Python :: 3.8
